simplemodelrouter/__init__.py
simplemodelrouter/base.py
simplemodelrouter/normalizers/__init__.py
simplemodelrouter/normalizers/base.py
simplemodelrouter/providers/anthropic.py
simplemodelrouter/providers/ollama.py
simplemodelrouter/providers/openai.py
simplemodelrouter/types.py
simplemodelrouter-0.1.3.dist-info/METADATA
simplemodelrouter-0.1.3.dist-info/WHEEL
simplemodelrouter-0.1.3.dist-info/RECORD
