Metadata-Version: 2.1
Name: simplemodelrouter
Version: 0.1.3
Summary: A Python library for interfacing with various LLM inference endpoints
License: Apache-2.0
Keywords: llm,ai,openai,anthropic,ollama
Author: Luke Hinds
Author-email: luke@stacklok.com
Requires-Python: >=3.10,<4.0
Classifier: Development Status :: 3 - Alpha
Classifier: Intended Audience :: Developers
Classifier: License :: OSI Approved :: Apache Software License
Classifier: Programming Language :: Python :: 3
Classifier: Programming Language :: Python :: 3.10
Classifier: Programming Language :: Python :: 3.11
Classifier: Programming Language :: Python :: 3.12
Classifier: Programming Language :: Python :: 3.13
Requires-Dist: httpx (>=0.25.0)
Requires-Dist: typing-extensions (>=4.0.0)
